README
setup.py
ctutlz/__init__.py
ctutlz/_version.py
ctutlz/ctlog.py
ctutlz/log_list_schema.json
ctutlz/really_all_logs.json
ctutlz/rfc6962.py
ctutlz.egg-info/PKG-INFO
ctutlz.egg-info/SOURCES.txt
ctutlz.egg-info/dependency_links.txt
ctutlz.egg-info/entry_points.txt
ctutlz.egg-info/requires.txt
ctutlz.egg-info/top_level.txt
ctutlz/scripts/__init__.py
ctutlz/scripts/ctloglist.py
ctutlz/scripts/decompose_cert.py
ctutlz/scripts/verify_scts.py
ctutlz/sct/__init__.py
ctutlz/sct/ee_cert.py
ctutlz/sct/signature_input.py
ctutlz/sct/verification.py
ctutlz/tls/__init__.py
ctutlz/tls/handshake.py
ctutlz/tls/handshake_openssl_build.py
ctutlz/tls/sctlist.py
ctutlz/utils/__init__.py
ctutlz/utils/encoding.py
ctutlz/utils/logger.py
ctutlz/utils/string.py
ctutlz/utils/tdf_bytes.py