Metadata-Version: 1.1
Name: ctutlz
Version: 0.9.6
Summary: Certificate Transparency utils library and scripts.
Home-page: https://github.com/theno/ctutlz
Author: Theodor Nolte
Author-email: ctutlz@theno.eu
License: MIT
Keywords: python development utilities library certificate-transparency ct signed-certificate-timestamp sct
Platform: UNKNOWN
Classifier: Development Status :: 3 - Alpha
Classifier: Intended Audience :: Developers
Classifier: Topic :: Software Development :: Libraries :: Python Modules
Classifier: License :: OSI Approved :: MIT License
Classifier: Programming Language :: Python :: 2
Classifier: Programming Language :: Python :: 2.6
Classifier: Programming Language :: Python :: 2.7
Classifier: Programming Language :: Python :: 3
Classifier: Programming Language :: Python :: 3.3
Classifier: Programming Language :: Python :: 3.4
Classifier: Programming Language :: Python :: 3.5
Classifier: Programming Language :: Python :: 3.6
